README.md
corefoundationasyncio.py
corefoundationselector.py
setup.py
corefoundationasyncio.egg-info/PKG-INFO
corefoundationasyncio.egg-info/SOURCES.txt
corefoundationasyncio.egg-info/dependency_links.txt
corefoundationasyncio.egg-info/requires.txt
corefoundationasyncio.egg-info/top_level.txt