Metadata-Version: 2.1
Name: corefoundationasyncio
Version: 0.0.1
Summary: CoreFoundation based selector and asyncio event loop
Home-page: https://github.com/alberthier/corefoundationasyncio
Author: Eric ALBER
Author-email: eric.alber@gmail.com
License: MIT
Platform: UNKNOWN
Classifier: Development Status :: 3 - Alpha
Classifier: Environment :: MacOS X :: Cocoa
Classifier: Intended Audience :: Developers
Classifier: Intended Audience :: Information Technology
Classifier: License :: OSI Approved :: MIT License
Classifier: Operating System :: MacOS :: MacOS X
Classifier: Programming Language :: Python
